Metadata-Version: 2.1
Name: stamp-processing
Version: 0.0.3
Summary: Stamp processing package
Home-page: https://github.com/sun-asterisk-research/stamp_processing/
Author: Sun* AI Research Team
Author-email: sun.converter.team@gmail.com
License: UNKNOWN
Project-URL: Bug Tracker, https://github.com/sun-asterisk-research/stamp_processing/issues
Platform: UNKNOWN
Classifier: Programming Language :: Python :: 3
Classifier: Operating System :: OS Independent
Requires-Python: >=3.7
Requires-Dist: gdown
Requires-Dist: Pillow (<=8.2.0opencv-python>=4.1.2.30)
Requires-Dist: torch (==1.8.1)
Requires-Dist: torchvision (==0.9.1)
Requires-Dist: fastai (==2.3.1)
Requires-Dist: numpy (>=1.20)
Requires-Dist: PyYAML (==5.4.1)
